README
setup.cfg
setup.py
greppy/__init__.py
greppy/grep.py
greppy/test_grep.py
greppy.egg-info/PKG-INFO
greppy.egg-info/SOURCES.txt
greppy.egg-info/dependency_links.txt
greppy.egg-info/entry_points.txt
greppy.egg-info/top_level.txt