Metadata-Version: 1.1
Name: greppy
Version: 0.1.3
Summary: A grep replica (I'd say clone, but not quite)
Home-page: http://github.com/ilovetux/greppy
Author: iLoveTux
Author-email: me@ilovetux.com
License: GPLv3
Keywords: grep regex
Platform: UNKNOWN
Classifier: Development Status :: 4 - Beta
Classifier: Topic :: Utilities
Classifier: License :: OSI Approved :: GNU General Public License v3 (GPLv3)
